{"coord":{"lon":28.0567,"lat":-26.1076},"weather":[{"id":803,"main":"Clouds","description":"broken clouds","icon":"04d"}],"base":"stations","main":{"temp":289.27,"feels_like":287.43,"temp_min":288.49,"temp_max":289.69,"pressure":1022,"humidity":19},"visibility":10000,"wind":{"speed":1.34,"deg":204,"gust":4.47},"clouds":{"all":81},"dt":1660568405,"sys":{"type":2,"id":2005523,"country":"ZA","sunrise":1660538211,"sunset":1660578480},"timezone":7200,"id":994858,"name":"Inanda","cod":200}

//https://api.openweathermap.org/data/2.5/weather?lat=-26.107567&lon=28.056702&appid=7fc358c2021588f7e85fbf678ce8c18d
